{
  "modId": 12912.0,
  "modName": "Lilith Spear - SAVEGAME",
  "summary": "Female Save",
  "descriptionHtml": "A Nice Looking Female Save\r\n\r\nRequired:\r\nFF_Mithra\r\nBella Better Females\r\nCBBE - Calentines Big Bottom Edition(Dont Need That Mutch Unless...)\r\nEnvisions Faces\r\nLovely Hair\r\nApachiiSkyHair\r\n\r\nRecomended:\r\n Beatiful Weapons By Hentai\r\n\r\nPlease Comment And if you havent already Endorse.\r\n\r\nLove you all! (No Homo)\r\n\r\nEdit: The armor that many have requested is an import from Vindictus:\r\nhttp://www.mediafire.com/?gb0bf15cm3c142x",
  "categoryId": "43",
  "version": "v1",
  "author": "Richuani",
  "createdUnix": "1331749287",
  "updatedUnix": "1331751570",
  "containsAdultContent": false,
  "uploadedBy": "richuani",
  "primaryFile": null,
  "files": [
    {
      "fileId": "43323",
      "name": "Lilith Savegame",
      "version": "v1.0",
      "categoryId": "1",
      "categoryName": "MAIN",
      "isPrimary": false,
      "size": "1349",
      "fileName": "Lilith Savegame-12912-v1-0.rar",
      "uploadedUnix": "1331751570",
      "modVersion": "v1.0",
      "virusScanUrl": "https://www.virustotal.com/file/62db02b7ea3cd2cc14c06e5d09434c97b6c34d02cd22d34fddfe53b0c362c9ac/analysis/1406749086/",
      "changelogHtml": null,
      "cdnName": "Nexus Global Content Delivery Network",
      "downloadUrl": "https://filedelivery.nexusmods.com/110/Lilith%20Savegame-12912-v1-0.rar?fid=43323&ttl=1535775225&ri=8192&rs=8192&setec=035ff7ad8e842a6e10e53fea8872ba95"
    }
  ]
}