{
  "modId": 19698.0,
  "modName": "Kaboom Spell",
  "summary": "New destruction Spell",
  "descriptionHtml": "new destruction spell buy it at whitterun dragonsreach --> Farengar",
  "categoryId": "75",
  "version": "1",
  "author": "Meiko n Mieko",
  "createdUnix": "1341108687",
  "updatedUnix": "1341108906",
  "containsAdultContent": false,
  "uploadedBy": "DarkNoirLcifer",
  "primaryFile": null,
  "files": [
    {
      "fileId": "71344",
      "name": "Kaboom",
      "version": "1",
      "categoryId": "1",
      "categoryName": "MAIN",
      "isPrimary": false,
      "size": "1",
      "fileName": "Kaboom-19698-1.rar",
      "uploadedUnix": "1341108906",
      "modVersion": "1",
      "virusScanUrl": "https://www.virustotal.com/file/0721c913d6c94d9e0389e5eb9a7ed58c2e7b94cf6fad6623e362941bae61ea0b/analysis/1406993285/",
      "changelogHtml": null,
      "cdnName": "Nexus Global Content Delivery Network",
      "downloadUrl": "https://filedelivery.nexusmods.com/110/Kaboom-19698-1.rar?fid=71344&ttl=1535787344&ri=8192&rs=8192&setec=728f5bb0164b79607ef55d65b44ed560"
    }
  ]
}