{
  "modId": 2299.0,
  "modName": "Khajiit Teat Retexture",
  "summary": "Adds some nipples to the stomachs of female Khajiit characters.",
  "descriptionHtml": "Adds some nipples to the stomachs of female Khajiit characters.\r\nCat\\'s have teats, Khajiit are cat people, so I thought it wasn\\'t a bad idea.\r\nIt\\'s not perfect but feel free to edit or recreate this mod with credit :D\r\n\r\nThis mod also requires a nude mod if you want to see the breast nipples.\r\nIf you choose one that already has a Khajiit texture, just install this mod over it.",
  "categoryId": "29",
  "version": "1",
  "author": "Hunterbait",
  "createdUnix": "1322790239",
  "updatedUnix": "1322790866",
  "containsAdultContent": true,
  "uploadedBy": "hunterbait93",
  "primaryFile": null,
  "files": [
    {
      "fileId": "6078",
      "name": "Khajiit Teats Zip",
      "version": "1",
      "categoryId": "1",
      "categoryName": "MAIN",
      "isPrimary": false,
      "size": "2900",
      "fileName": "Khajiit Teats Zip-2299-1.zip",
      "uploadedUnix": "1322790866",
      "modVersion": "1",
      "virusScanUrl": "https://www.virustotal.com/file/b5e6eded50511009ad684190b84399af83b447c3deed4d4552170ac54c73ce02/analysis/1406467805/",
      "changelogHtml": null,
      "cdnName": "Nexus Global Content Delivery Network",
      "downloadUrl": "https://filedelivery.nexusmods.com/110/Khajiit%20Teats%20Zip-2299-1.zip?fid=6078&ttl=1535756498&ri=8192&rs=8192&setec=313e625382586f1e45e1c524112a8bb2"
    }
  ]
}