{
  "modId": 51184.0,
  "modName": "Jarls Clothes Replacer",
  "summary": "No more naked Jarl arms&#33;&#33;&#33;",
  "descriptionHtml": "Versions available for:\r<br />\r<br />[color=#6aa84f][size=4][b]Vanilla[/b][/size][/color][size=4]\r<br />[color=#ffd966][b]Elaborate Textiles[/b] [/color][i]by [/i][b][i]Miss Obsidienne[/i] - [url=http://www.nexusmods.com/skyrim/mods/19826/?]http://www.nexusmods.com/skyrim/mods/19826/?[/url][/b]\r<br />[color=#ff7700][b]Rustic Clothing[/b][/color] [i]by Gamwich[/i] - [/size][size=4][url=http://www.nexusmods.com/skyrim/mods/69784/?]http://www.nexusmods.com/skyrim/mods/69784/?[/url][/size]\r<br />\r<br />[b]If you like these awesome textures check out these author&#39;s complete mods at their respective links&#33;[/b]\r<br />\r<br />Special Request: Changing the mod &#34;Jarl Clothes with Sleeves - Emperor Retexture by frank zunge&#34; \r<br />\r<br />into a simple replacer an not a stand alone. \r<br />\r<br />Install\r<br />=======\r<br />\r<br />Allow NMM to install. (recommended)\r<br />\r<br />Uninstall\r<br />=========\r<br />\r<br />Use NMM to uninstall...again...recommended.\r<br />\r<br />\r<br />History\r<br />=======\r<br />\r<br />1.0, 2014/02/16 - Initial release.\r<br />2.0, 2014/07/29 - Elaborate Textiles release.\r<br />3.0, 2015/11/29 - Rustic Clothing release.\r<br />\r<br />Contact\r<br />=======\r<br />You can find me on skyrim.nexusmods.com or Steam as JadeRoyale\r<br />\r<br />\r<br />Credits\r<br />=======\r<br />Miss Obsidienne for the Elaborate Textile textures.\r<br />Frank Zunge for creating the original Jarl Clothes with Sleeves mod.\r<br />Bethesda for creating Skyrim...awesome game.\r<br />\r<br />Licensing/Legal\r<br />===============\r<br />This is originally the work of Frank Zunge and Miss Obsidienne. I am using it under the free use permission. ",
  "categoryId": "60",
  "version": "3.0",
  "author": "JadeRoyale",
  "createdUnix": "1392590458",
  "updatedUnix": "1448849073",
  "containsAdultContent": false,
  "uploadedBy": "jaderoyale",
  "primaryFile": null,
  "files": [
    {
      "fileId": "1000097390",
      "name": "Jarls Clothes Replacer",
      "version": "",
      "categoryId": "1",
      "categoryName": "MAIN",
      "isPrimary": false,
      "size": "3693",
      "fileName": "Jarls Clothes Replacer-51184-.7z",
      "uploadedUnix": "1392590343",
      "modVersion": null,
      "virusScanUrl": "https://www.virustotal.com/file/fa69d4e3977b284da44d56dd9fa52fb0c72a0a9025a9fdbd1eedc11963d93409/analysis/1407936783/",
      "changelogHtml": null,
      "cdnName": "Nexus Global Content Delivery Network",
      "downloadUrl": "https://filedelivery.nexusmods.com/110/Jarls%20Clothes%20Replacer-51184-.7z?fid=1000097390&ttl=1535833373&ri=8192&rs=8192&setec=9230a09834c419134b31e7b57f5cc299"
    },
    {
      "fileId": "1000119436",
      "name": "Elaborate Textiles - Jarls New Clothes",
      "version": "2.0",
      "categoryId": "1",
      "categoryName": "MAIN",
      "isPrimary": false,
      "size": "3510",
      "fileName": "Elaborate Textiles - Jarls New Clothes-51184-2-0.zip",
      "uploadedUnix": "1406440161",
      "modVersion": "2.0",
      "virusScanUrl": "https://www.virustotal.com/file/c4f86d04bf9538b65b4291cc87e6affb0ab81fd37a60aeecd6acc4573be627e1/analysis/1406440209/",
      "changelogHtml": null,
      "cdnName": "Nexus Global Content Delivery Network",
      "downloadUrl": "https://filedelivery.nexusmods.com/110/Elaborate%20Textiles%20-%20Jarls%20New%20Clothes-51184-2-0.zip?fid=1000119436&ttl=1535833374&ri=8192&rs=8192&setec=f3398c479b3f5fcda1e5873fd0e19fdf"
    },
    {
      "fileId": "1000186456",
      "name": "Rustic Clothing - Jarls New Clothes 2k",
      "version": "3.0",
      "categoryId": "1",
      "categoryName": "MAIN",
      "isPrimary": false,
      "size": "9369",
      "fileName": "Rustic Clothing - Jarls New Clothes-51184-2-0.rar",
      "uploadedUnix": "1448846713",
      "modVersion": "3.0",
      "virusScanUrl": "https://www.virustotal.com/file/71705707f0f18e3180c6ade417328e4fb035ee11fb025a11a4ebcf0f96b755f7/analysis/1448846779/",
      "changelogHtml": null,
      "cdnName": "Nexus Global Content Delivery Network",
      "downloadUrl": "https://filedelivery.nexusmods.com/110/Rustic%20Clothing%20-%20Jarls%20New%20Clothes-51184-2-0.rar?fid=1000186456&ttl=1535833374&ri=8192&rs=8192&setec=d1bf894843474a18ed04f21d901a40c8"
    },
    {
      "fileId": "1000186458",
      "name": "Rustic Clothing - Jarls New Clothes 1k",
      "version": "3.0",
      "categoryId": "1",
      "categoryName": "MAIN",
      "isPrimary": false,
      "size": "6117",
      "fileName": "Rustic Clothing - Jarls New Clothes-51184-3-0.rar",
      "uploadedUnix": "1448849073",
      "modVersion": "3.0",
      "virusScanUrl": "https://www.virustotal.com/file/da5512d15c89754a1fc9d24cfa8a7dda87eb943bf7574f523b571acb131e3ad9/analysis/1448849107/",
      "changelogHtml": null,
      "cdnName": "Nexus Global Content Delivery Network",
      "downloadUrl": "https://filedelivery.nexusmods.com/110/Rustic%20Clothing%20-%20Jarls%20New%20Clothes-51184-3-0.rar?fid=1000186458&ttl=1535833374&ri=8192&rs=8192&setec=e8aafbb40d004ba4378633066b35127e"
    }
  ]
}