{
  "modId": 5976.0,
  "modName": "Main Menu Music Replacement_The Bard Song cover by Malukah",
  "summary": "Replaces the music on the main menu with a soothing cover of the Bard Song.",
  "descriptionHtml": "It replaces the music on the main menu, and it can also be played in a tavern. If you haven\\'t heard the song, here\\'s the link: \r\nhttp://www.youtube.com/watch?v=4z9TdDCWN7g\r\n\r\nBe aware that I DID NOT make the song. I just did the modding.\r\n\r\n-Installation-\r\nDrag and drop the Music folder into your Data folder.",
  "categoryId": "61",
  "version": "1",
  "author": "Fuzion",
  "createdUnix": "1326344593",
  "updatedUnix": "1326344796",
  "containsAdultContent": false,
  "uploadedBy": "fusion407",
  "primaryFile": null,
  "files": [
    {
      "fileId": "19062",
      "name": "The Bard Song cover by Malukah",
      "version": "1",
      "categoryId": "1",
      "categoryName": "MAIN",
      "isPrimary": false,
      "size": "1393",
      "fileName": "The Bard Song cover by Malukah-5976-1.rar",
      "uploadedUnix": "1326344796",
      "modVersion": "1",
      "virusScanUrl": "https://www.virustotal.com/file/0fa8ff6cf632b1d0b329037261d116708e285014d589a2e8c4b56748d6d5e42c/analysis/1406604572/",
      "changelogHtml": null,
      "cdnName": "Nexus Global Content Delivery Network",
      "downloadUrl": "https://filedelivery.nexusmods.com/110/The%20Bard%20Song%20cover%20by%20Malukah-5976-1.rar?fid=19062&ttl=1535763121&ri=8192&rs=8192&setec=6f3490c82b0c3a3cf59e56a9a1eb1d4c"
    }
  ]
}