{
  "modId": 6609.0,
  "modName": "Wolfbane",
  "summary": "Adds a new greatsword to the game.",
  "descriptionHtml": "Was planning on releasing this later as a custom quest reward, you know, once CK comes out and i know how to make quests.\r\nAt the minute it\\'s just a standalone greatsword.\r\nFound under daedra category.\r\nThought i\\'d put it out there to see the response.\r\n\r\nExtract to data folder.\r\n\r\nLinks to my other files\r\nhttp://www.skyrimnexus.com/downloads/file.php?id=6124\r\nhttp://www.skyrimnexus.com/downloads/file.php?id=5810\r\nhttp://www.skyrimnexus.com/downloads/file.php?id=5952",
  "categoryId": "55",
  "version": "1.0",
  "author": "thebrommers",
  "createdUnix": "1327042496",
  "updatedUnix": "1327042579",
  "containsAdultContent": false,
  "uploadedBy": "thebrommers",
  "primaryFile": null,
  "files": [
    {
      "fileId": "21379",
      "name": "Wolfbane",
      "version": "1.0",
      "categoryId": "1",
      "categoryName": "MAIN",
      "isPrimary": false,
      "size": "3801",
      "fileName": "Wolfbane-6609-1-0.zip",
      "uploadedUnix": "1327042579",
      "modVersion": "1.0",
      "virusScanUrl": "https://www.virustotal.com/file/9f694fde4dd3dccf657b8870ffe8e6b67aab0f446df902414fc5a39c37094687/analysis/1406625067/",
      "changelogHtml": null,
      "cdnName": "Nexus Global Content Delivery Network",
      "downloadUrl": "https://filedelivery.nexusmods.com/110/Wolfbane-6609-1-0.zip?fid=21379&ttl=1535764149&ri=8192&rs=8192&setec=cd7bf7e8419313b77f494090e902113a"
    }
  ]
}