{
  "modId": 76740.0,
  "modName": "Felix The Cat",
  "summary": "Just a small mod a made. It&#39;s a follower of my cat. You can find him in the Bannered Mare.",
  "descriptionHtml": "This is my first ever uploaded mod. It&#39;s just a small follower mod that adds in Felix the cat. Felix is my cat in real life and so I made him into a follower. You can find him resting in the Bannered Mare. Enjoy&#33;",
  "categoryId": "96",
  "version": "1.02",
  "author": "Linc7991",
  "createdUnix": "1467340607",
  "updatedUnix": "1467340501",
  "containsAdultContent": false,
  "uploadedBy": "Linc7991",
  "primaryFile": null,
  "files": [
    {
      "fileId": "1000211692",
      "name": "FelixTheCat",
      "version": "1.02",
      "categoryId": "1",
      "categoryName": "MAIN",
      "isPrimary": false,
      "size": "1",
      "fileName": "FelixTheCat-76740-1-02.zip",
      "uploadedUnix": "1467340501",
      "modVersion": "1.02",
      "virusScanUrl": "https://www.virustotal.com/file/2bc5fffdbbe74e1e432aedd1a7483651d3f08894247c33bc7c1ab83f265643c9/analysis/1467340505/",
      "changelogHtml": null,
      "cdnName": "Nexus Global Content Delivery Network",
      "downloadUrl": "https://filedelivery.nexusmods.com/110/FelixTheCat-76740-1-02.zip?fid=1000211692&ttl=1535865460&ri=8192&rs=8192&setec=248ab471e8894a97d6cfae445446acf1"
    }
  ]
}