{
  "modId": 7678.0,
  "modName": "Toasted Dragonplate - Hot and Smoky Recolor",
  "summary": "An orange and black, lightly toasted recolor of the Dragonplate armor.",
  "descriptionHtml": "A recolor of http://skyrim.nexusmods.com/downloads/file.php?id=305\r\n\r\nI tried the link above, and plenty of other Dragonplate textures, and nothing really felt right to me. So I tried my hand at recoloring, and revamped the harsh reds and blacks of Dragonbone Armor in Fire into a deliciously cooled-off, dry toasted bone look.\r\n\r\nEnjoy the forge-smoked bone look this retexture gives you, and let me know what you think.\r\n\r\nIf you like this, check out my other retexture:\r\nhttp://skyrim.nexusmods.com/downloads/file.php?id=7665",
  "categoryId": "54",
  "version": "1.0",
  "author": "wetsail",
  "createdUnix": "1328257928",
  "updatedUnix": "1328258110",
  "containsAdultContent": false,
  "uploadedBy": "wetsail",
  "primaryFile": null,
  "files": [
    {
      "fileId": "25480",
      "name": "Toasted Dragonplate",
      "version": "",
      "categoryId": "1",
      "categoryName": "MAIN",
      "isPrimary": false,
      "size": "6182",
      "fileName": "Toasted Dragonplate-7678-1.zip",
      "uploadedUnix": "1328258110",
      "modVersion": null,
      "virusScanUrl": "https://www.virustotal.com/file/4c07ff7a8df2614d32d88cb35dd0b9442763a25550b57944f2dab30ff31dc66b/analysis/1406655439/",
      "changelogHtml": null,
      "cdnName": "Nexus Global Content Delivery Network",
      "downloadUrl": "https://filedelivery.nexusmods.com/110/Toasted%20Dragonplate-7678-1.zip?fid=25480&ttl=1535765897&ri=8192&rs=8192&setec=472d1d0fa2d0e633ab6d3b9ce6e963c6"
    }
  ]
}