{
  "modId": 82649.0,
  "modName": "The Shadow of Meresis ITA",
  "summary": "Traduzione in italiano",
  "descriptionHtml": "[size=6]The Shadow of Meresis ITA\r<br />[b] [/b][/size]\r<br /> \r<br />[size=3][b]Questa è la traduzione italiana del mod The Shadow of Meresis[/b] [b] by [url=http://www.nexusmods.com/skyrim/users/2840957/?]Hebrock[/url] [/b][b]che potete [/b][b]scaricare da[u] [url=http://www.nexusmods.com/skyrim/mods/36843/?]http://www.nexusmods.com/skyrim/mods/36843/?[/url].\r<br />[/u][/b][/size][size=3]Svelate l&#39;oscuro mistero che si cela dietro un&#39;antico amuleto&#33; \r<br />\r<br />INSTALLAZIONE:\r<br />\r<br />\r<br />1) Installare la mod originale\r<br />2) Sovrascrivere il file tradotto in Skyrim/Data.[/size]",
  "categoryId": "35",
  "version": "1.1.2",
  "author": "Hebrock",
  "createdUnix": "1489047919",
  "updatedUnix": "1489047914",
  "containsAdultContent": false,
  "uploadedBy": "mitsurai",
  "primaryFile": null,
  "files": [
    {
      "fileId": "1000238636",
      "name": "Shadow of Meresis ITA",
      "version": "1.1.2",
      "categoryId": "1",
      "categoryName": "MAIN",
      "isPrimary": false,
      "size": "1414",
      "fileName": "Shadow of Meresis ITA-82649-1-1-2.zip",
      "uploadedUnix": "1489047914",
      "modVersion": "1.1.2",
      "virusScanUrl": "https://www.virustotal.com/file/8a2461ce030ed4ba76d744044a636b027f7ff3eca1fdbb1b25e93aadce240664/analysis/1489048088/",
      "changelogHtml": null,
      "cdnName": "Nexus Global Content Delivery Network",
      "downloadUrl": "https://filedelivery.nexusmods.com/110/Shadow%20of%20Meresis%20ITA-82649-1-1-2.zip?fid=1000238636&ttl=1535871420&ri=8192&rs=8192&setec=544a54ae27ee9d8e7213cc5b539c7249"
    }
  ]
}