{
  "modId": 88005.0,
  "modName": "God Gifted Armor",
  "summary": "These armor was created by the Gods to help the Dragonborn on his quests.",
  "descriptionHtml": "These armor sets enchant everything but smithing, alchemy, unarmed, and heavy armor. They require that you learn steel smithing to make and arcane smithing to upgrade. They require you to use a grand soul gem filled to make and upgrade them.\n<br />The Magus set is Dragonscale Armor\n<br />The Gifted set is Elven Armor\n<br />The Revered Set is Dwarven Armor\n<br />The Summoned Set is Daedric Armor\n<br />The New set adds enchantments to Heavy Armor\n<br />Adds SpellBreaker Ench on the shields",
  "categoryId": "54",
  "version": "2.0",
  "author": "Redraga",
  "createdUnix": "1511329181",
  "updatedUnix": "1517487671",
  "containsAdultContent": false,
  "uploadedBy": "redraga",
  "primaryFile": null,
  "files": [
    {
      "fileId": "1000260294",
      "name": "Magus_Gifted_Armor",
      "version": "1.0",
      "categoryId": "6",
      "categoryName": null,
      "isPrimary": false,
      "size": "4",
      "fileName": "Magus_Gifted_Armor.7z-88005-1-0.7z",
      "uploadedUnix": "1511328657",
      "modVersion": "1.0",
      "virusScanUrl": "https://www.virustotal.com/file/522ea8acfb9a3a3fd97e4824847023847dff462bd1f1c26e432911004649b5c9/analysis/1511328662/",
      "changelogHtml": null,
      "cdnName": "Nexus Global Content Delivery Network",
      "downloadUrl": "https://filedelivery.nexusmods.com/110/Magus_Gifted_Armor.7z-88005-1-0.7z?fid=1000260294&ttl=1535877067&ri=8192&rs=8192&setec=17d592df763901cceb93a94abf4cb068"
    },
    {
      "fileId": "1000262031",
      "name": "God Gifted Armor 1.5",
      "version": "1.5",
      "categoryId": "4",
      "categoryName": "OLD_VERSION",
      "isPrimary": false,
      "size": "6",
      "fileName": "God Gifted Armor 1.5-88005-1-5.7z",
      "uploadedUnix": "1513378008",
      "modVersion": "1.5",
      "virusScanUrl": "https://www.virustotal.com/file/894bcdcc9f000ab23fa6fc8df757ff471cf30cb5757af3cbb9ee4dcf0bd7c4a6/analysis/1513378022/",
      "changelogHtml": null,
      "cdnName": "Nexus Global Content Delivery Network",
      "downloadUrl": "https://filedelivery.nexusmods.com/110/God%20Gifted%20Armor%201.5-88005-1-5.7z?fid=1000262031&ttl=1535877067&ri=8192&rs=8192&setec=a65adf81a58376feaf6ecbd11b4dfcec"
    },
    {
      "fileId": "1000265252",
      "name": "God Gifted Armor 2.0",
      "version": "2.0",
      "categoryId": "1",
      "categoryName": "MAIN",
      "isPrimary": false,
      "size": "7",
      "fileName": "God Gifted Armor 2.0-88005-2-0.zip",
      "uploadedUnix": "1517487671",
      "modVersion": "2.0",
      "virusScanUrl": "https://www.virustotal.com/file/1a52ebd186ad77e947c18741829dae154277f015d4b5fca6ae20f747e81de1e9/analysis/1517487902/",
      "changelogHtml": null,
      "cdnName": "Nexus Global Content Delivery Network",
      "downloadUrl": "https://filedelivery.nexusmods.com/110/God%20Gifted%20Armor%202.0-88005-2-0.zip?fid=1000265252&ttl=1535877067&ri=8192&rs=8192&setec=f96d86c96e9b8b286bbb1096b0b5b202"
    }
  ]
}