{
  "modId": 8983.0,
  "modName": "Spirit World Redone",
  "summary": "A work in project mod that add a new land like sovngarde for your player to live.",
  "descriptionHtml": "[center][img]http://i43.tinypic.com/b4dmki.jpg[/img][/center]\r\n\r\n[color=#00f44f]Description:[/color] \r\n[color=#0b9669]-------------------[/color] \r\nHey guys, this is my version of Spirit Realm House mod.\r\n\r\nI just loved the idea behind the mod but there were some things I wanted to improve, so I made my own version.\r\n\r\nIn this release, I changed the entrace to Spirit World to a portal like the one at Skuldafn because I just love the animation of that portal and I\\'ve been wainting for the CK to make this possible. (Took me a LOT of time to get the scripting right)\r\n\r\nYou need to have a Dragon Priest Staff in order to open it, and you can then retrieve it and close the portal.\r\n\r\n\r\n[color=#00f44f]Support:[/color] \r\n[color=#0b9669]-------------------[/color] \r\nRemember, this mod was based from [url=http://skyrim.nexusmods.com/downloads/file.php?id=8392]BillyJunes\\'s Spirit Realm House mod[/url] , so if you like this make sure you endorse is work ;)\r\n\r\n\r\n[color=#00f44f]Update Notes:[/color] \r\n[color=#0b9669]-------------------[/color]\r\nIf you have a version prior to 1.2 you must first retrive any item you have at Spirit World and leave the place, only then you can update.\r\nIf you have 1.2 or higher you only need to replace the files.\r\n\r\n\r\n[color=#00f44f]Features so Far:[/color] \r\n[color=#0b9669]-------------------[/color] \r\n[list] \r\n[*] Fully animated portal to Spirit World    \r\n[*] A new house like Hall of Vallor in sovngarde.\r\n[*] 12 Weapon Racks\r\n[*] 6 Weapon Displays\r\n[*] 2 Dagger Displays \r\n[*] 4 Manequins\r\n[*] 2 Merchants (BlackSmith/Alchemy) - New v1.3\r\n\r\n[/list]\r\n\r\n\r\n[color=#00f44f]Planned Features:[/color] \r\n[color=#0b9669]-------------------[/color] \r\n[list]\r\n[*] Make a quest to get the Dragon Priest Staff that you need in order to open the gate to Spirit World\r\n\r\n[*] Companion Navmesh to allow your companion to follow you (25% done)\r\n\r\n[*] Npc\\'s in Spirit Word like merchants and hired companions\r\n\r\n[*] New rooms with tons of new stuff and features\r\n[/list]\r\n\r\n\r\n[color=#00f44f]Versions:[/color] \r\n[color=#0b9669]-------------------[/color] \r\n1.3\r\n[list] \r\n[*] Complete Spirit World Overhaul (Garden, War Room, Dinner Room and Market)\r\n[*] Added 2 Merchants\r\n[/list]\r\n\r\n1.2\r\n[list] \r\n[*] Added 2 Dagger Displays\r\n[*] Changed file type to .esm\r\n[*] Added Optional File to remove All whirlwind effects (hope this fix the fuzzy lines)\r\n[/list] \r\n\r\n1.1\r\n[list] \r\n[*] Added 6 Weapon Displays    \r\n[*] Added 14 Weapon Racks\r\n[*] Added 4 Mannequins\r\n[*] Changed a bit the dinner room\r\n[*] Added Navigation Mesh (Not yet finished)\r\n[*] Changed file type to .bsa\r\n[/list]\r\n\r\n\r\n[color=#00f44f]Install Notes:[/color] \r\n[color=#0b9669]-------------------[/color]\r\nJust drop Data folder at your Skyrim location\r\n\r\n\r\nStay tunned ;)",
  "categoryId": "67",
  "version": "1.3",
  "author": "3nvy",
  "createdUnix": "1328989951",
  "updatedUnix": "1329602826",
  "containsAdultContent": false,
  "uploadedBy": "3nvy",
  "primaryFile": null,
  "files": [
    {
      "fileId": "29107",
      "name": "spiritworldredone-1_1",
      "version": "1.1",
      "categoryId": "4",
      "categoryName": "OLD_VERSION",
      "isPrimary": false,
      "size": "65",
      "fileName": "spiritworldredone-1_1-8983.rar",
      "uploadedUnix": "1328990183",
      "modVersion": "1.1",
      "virusScanUrl": "https://www.virustotal.com/file/5fab67bde8f3448d0a3bbeab4440492a7a4252450fcd559af3c9c1fa03ff37c2/analysis/1406670786/",
      "changelogHtml": null,
      "cdnName": "Nexus Global Content Delivery Network",
      "downloadUrl": "https://filedelivery.nexusmods.com/110/spiritworldredone-1_1-8983.rar?fid=29107&ttl=1535768156&ri=8192&rs=8192&setec=4babd19fb2b4406bd4309eda94473efd"
    },
    {
      "fileId": "29110",
      "name": "spiritworldredone-1_0",
      "version": "1.0",
      "categoryId": "4",
      "categoryName": "OLD_VERSION",
      "isPrimary": false,
      "size": "61",
      "fileName": "spiritworldredone-1_0-8983-1-0.rar",
      "uploadedUnix": "1328990730",
      "modVersion": "1.0",
      "virusScanUrl": "https://www.virustotal.com/file/c362e4eef16d1ad907704cbe77c3f0ef048b11fc573a88cdb55e701e9379ef9c/analysis/1406670789/",
      "changelogHtml": null,
      "cdnName": "Nexus Global Content Delivery Network",
      "downloadUrl": "https://filedelivery.nexusmods.com/110/spiritworldredone-1_0-8983-1-0.rar?fid=29110&ttl=1535768157&ri=8192&rs=8192&setec=7871e0695efc6e3d354214bd354ede2e"
    },
    {
      "fileId": "29237",
      "name": "spiritworldredone-1_2",
      "version": "1.2",
      "categoryId": "4",
      "categoryName": "OLD_VERSION",
      "isPrimary": false,
      "size": "64",
      "fileName": "spiritworldredone-1_2-8983.rar",
      "uploadedUnix": "1329005152",
      "modVersion": "1.2",
      "virusScanUrl": "https://www.virustotal.com/file/034221d468836981d145b541be8e7b9d9a24d8fdbf9919802fa168bf922df474/analysis/1406671580/",
      "changelogHtml": null,
      "cdnName": "Nexus Global Content Delivery Network",
      "downloadUrl": "https://filedelivery.nexusmods.com/110/spiritworldredone-1_2-8983.rar?fid=29237&ttl=1535768157&ri=8192&rs=8192&setec=2fc716dc00f747841945fcc4e880a1c5"
    },
    {
      "fileId": "29239",
      "name": "SWR - NoFuzzyLines",
      "version": "",
      "categoryId": "3",
      "categoryName": "OPTIONAL",
      "isPrimary": false,
      "size": "1",
      "fileName": "SWR - NoFuzzyLines-8983-1.rar",
      "uploadedUnix": "1329005225",
      "modVersion": null,
      "virusScanUrl": "https://www.virustotal.com/file/521823fba0d2100fed9fde998cb348805450081cd57676c2635d60ff97b915ca/analysis/1406671682/",
      "changelogHtml": null,
      "cdnName": "Nexus Global Content Delivery Network",
      "downloadUrl": "https://filedelivery.nexusmods.com/110/SWR%20-%20NoFuzzyLines-8983-1.rar?fid=29239&ttl=1535768158&ri=8192&rs=8192&setec=2aca72bb995a8cca84a2ab8fcd7c8979"
    },
    {
      "fileId": "32244",
      "name": "spiritworldredone-1_3",
      "version": "",
      "categoryId": "1",
      "categoryName": "MAIN",
      "isPrimary": false,
      "size": "73",
      "fileName": "spiritworldredone-1_3-8983-1.zip",
      "uploadedUnix": "1329432279",
      "modVersion": null,
      "virusScanUrl": "https://www.virustotal.com/file/c755bb5ee87dd0b6b9482a33e9acd36c07ae694b37c80ffc7bfde89d0be12a44/analysis/1406688248/",
      "changelogHtml": null,
      "cdnName": "Nexus Global Content Delivery Network",
      "downloadUrl": "https://filedelivery.nexusmods.com/110/spiritworldredone-1_3-8983-1.zip?fid=32244&ttl=1535768158&ri=8192&rs=8192&setec=81d73403c380ea6add6fe1fd2d193102"
    },
    {
      "fileId": "33345",
      "name": "SWR - Scripts",
      "version": "1",
      "categoryId": "3",
      "categoryName": "OPTIONAL",
      "isPrimary": false,
      "size": "4",
      "fileName": "SWR - Scripts-8983-1.zip",
      "uploadedUnix": "1329602826",
      "modVersion": "1",
      "virusScanUrl": "https://www.virustotal.com/file/47a3ce91b98427c13a0bae0351d7405b20c16899aca133f1ac48a062d418dba5/analysis/1406693831/",
      "changelogHtml": null,
      "cdnName": "Nexus Global Content Delivery Network",
      "downloadUrl": "https://filedelivery.nexusmods.com/110/SWR%20-%20Scripts-8983-1.zip?fid=33345&ttl=1535768159&ri=8192&rs=8192&setec=374c90cbbc8d45aa081c83a22d6d6132"
    }
  ]
}