{
  "modId": 92312.0,
  "modName": "Skyrim Martial Arts H2H Animations",
  "summary": "Why does the Dragonborn fight the same as everyone else? Shouldn't the Dragonborn use a different fighting style?",
  "descriptionHtml": "Just some simple changes. The goal here is to stay as close to the vanilla key frames as possible to prevent OP animation changes while at the same time include the essence of different fighting techniques.\n<br />\n<br />\n<br />Released: \n<br />Boxing (Orthodox Stance) 7/3/2018\n<br />\n<br />Upcoming Releases:\n<br />Boxing (South Paw)\n<br />Krav Maga\n<br />Muay Thai\n<br />GLIMA (Scandinavian martial art used by the vikings)\n<br />\n<br />\n<br />\n<br />Planned ideas:\n<br />H2H blocking\n<br />Blocking Animations",
  "categoryId": "51",
  "version": "1",
  "author": "Pukes",
  "createdUnix": "1530638604",
  "updatedUnix": "1530638604",
  "containsAdultContent": false,
  "uploadedBy": "Pukes",
  "primaryFile": null,
  "files": []
}